vissim2gmns/__init__.py
vissim2gmns/_vissim2geojson.py
vissim2gmns/func_lib/__init__.py
vissim2gmns/func_lib/cvt_fhz.py
vissim2gmns/func_lib/cvt_fzp.py
vissim2gmns/func_lib/cvt_fzp_deprecated.py
vissim2gmns/func_lib/cvt_inpx.py
vissim2gmns/func_lib/geocoding_vissim_coord.py
vissim2gmns-1.5.6.dist-info/licenses/LICENSE
vissim2gmns-1.5.6.dist-info/METADATA
vissim2gmns-1.5.6.dist-info/WHEEL
vissim2gmns-1.5.6.dist-info/top_level.txt
vissim2gmns-1.5.6.dist-info/RECORD
