Metadata-Version: 2.4
Name: vissim2gmns
Version: 1.5.6
Summary: vissim2gmns converts VISSIM files (.inpx, .fzp, .fhz) into GMNS format with WGS 1984 coordinates for easy GIS visualization and analysis.
Author: Xiangyong Luo
Author-email: Xiangyong Luo <luoxiangyong01@gmail.com>
Maintainer-email: Xiangyong Luo <luoxiangyong01@gmail.com>
Project-URL: Homepage, https://github.com/xyluo25/vissim2gmns
Project-URL: Documentation, https://vissim2gmns.readthedocs.io/en/latest/
Project-URL: Bug Tracker, https://github.com/xyluo25/vissim2gmns/issues
Project-URL: Download, https://www.pepy.tech/projects/vissim2gmns
Keywords: VISSIM,GMNS,Visualization,Conversion,Traffic Simulation,Analysis
Classifier: Programming Language :: Python :: 3
Classifier: Programming Language :: Python :: 3.10
Classifier: Programming Language :: Python :: 3.11
Classifier: Programming Language :: Python :: 3.12
Classifier: Programming Language :: Python :: 3.13
Classifier: Operating System :: OS Independent
Requires-Python: >=3.10
License-File: LICENSE
Requires-Dist: geopandas
Requires-Dist: pandas
Requires-Dist: Shapely
Requires-Dist: pyufunc
Provides-Extra: base
Requires-Dist: pandas; extra == "base"
Requires-Dist: pyufunc; extra == "base"
Requires-Dist: geopandas; extra == "base"
Requires-Dist: Shapely; extra == "base"
Dynamic: author
Dynamic: license-file
Dynamic: requires-python
